[
  {
    "label": "Fraction",
    "i18nKey": "sampleMathFraction",
    "icon": "f(x)",
    "enabled": true,
    "code": "x = \\frac{-b \\pm \\sqrt{b^2 - 4ac}}{2a}"
  },
  {
    "label": "Sum",
    "i18nKey": "sampleMathSum",
    "icon": "\u03a3",
    "enabled": true,
    "code": "\\sum_{k=1}^{n} k = \\frac{n(n+1)}{2}"
  },
  {
    "label": "Integral",
    "i18nKey": "sampleMathIntegral",
    "icon": "\u222b",
    "enabled": true,
    "code": "\\int_{a}^{b} f(x) \\, dx = F(b) - F(a)"
  },
  {
    "label": "Matrix",
    "i18nKey": "sampleMathMatrix",
    "icon": "[ ]",
    "enabled": true,
    "code": "\\begin{pmatrix} a & b \\\\ c & d \\end{pmatrix} \\begin{pmatrix} x \\\\ y \\end{pmatrix} = \\begin{pmatrix} ax + by \\\\ cx + dy \\end{pmatrix}"
  },
  {
    "label": "Limit",
    "i18nKey": "sampleMathLimit",
    "icon": "lim",
    "enabled": true,
    "code": "\\lim_{x \\to 0} \\frac{\\sin x}{x} = 1"
  },
  {
    "label": "Derivative",
    "i18nKey": "sampleMathDerivative",
    "icon": "\u2202",
    "enabled": true,
    "code": "\\frac{\\partial f}{\\partial x} = \\lim_{h \\to 0} \\frac{f(x+h, y) - f(x, y)}{h}"
  },
  {
    "label": "Cases",
    "i18nKey": "sampleMathCases",
    "icon": "{",
    "enabled": true,
    "code": "f(x) = \\begin{cases} x^2 & \\text{if } x \\geq 0 \\\\ -x^2 & \\text{if } x < 0 \\end{cases}"
  },
  {
    "label": "Parabola",
    "i18nKey": "sampleMathParabola",
    "icon": "📈",
    "enabled": true,
    "code": "y = x^{2} - 3x + 1"
  },
  {
    "label": "Trigonometric",
    "i18nKey": "sampleMathTrigGraph",
    "icon": "📈",
    "enabled": true,
    "code": "y = a \\cdot \\sin(x) + \\cos(2x)"
  },
  {
    "label": "Circle",
    "i18nKey": "sampleMathCircle",
    "icon": "📈",
    "enabled": true,
    "code": "x^{2} + y^{2} = 4"
  },
  {
    "label": "Polar",
    "i18nKey": "sampleMathPolar",
    "icon": "📈",
    "enabled": true,
    "code": "r = 1 + \\cos(\\theta)"
  },
  {
    "label": "Parametric",
    "i18nKey": "sampleMathParametric",
    "icon": "📈",
    "enabled": true,
    "code": "\\begin{cases} x = \\cos(t) \\\\ y = \\sin(t) \\end{cases}"
  },
  {
    "label": "3D Surface",
    "i18nKey": "sampleMath3DSurface",
    "icon": "📈",
    "enabled": true,
    "code": "z = \\sin(x) \\cdot \\cos(y)"
  }
]
